nlproc_tools/__init__.py
nlproc_tools/convert.py
nlproc_tools/dataloader.py
nlproc_tools/names.py
nlproc_tools/util.py
nlproc_tools/datasets/__init__.py
nlproc_tools/datasets/da-san-martino-etal-2019.py
nlproc_tools/datasets/frank.py
nlproc_tools/datasets/mqm.py
nlproc_tools/datasets/salsa.py
nlproc_tools/datasets/scarecrow.py
nlproc_tools/datasets/snac.py
nlproc_tools/datasets/wu-etal-2023.py
nlproc_tools-0.1.0.dist-info/LICENSE
nlproc_tools-0.1.0.dist-info/METADATA
nlproc_tools-0.1.0.dist-info/WHEEL
nlproc_tools-0.1.0.dist-info/top_level.txt
nlproc_tools-0.1.0.dist-info/RECORD
