Metadata-Version: 2.1
Name: nlproc-tools
Version: 0.1.0
Summary: Load and manage data collection with nlproc.tools
Home-page: https://github.com/davidheineman/nlproc.tools
Author: David Heineman
Author-email: dheineman3@gatech.edu
Project-URL: Bug Tracker, https://github.com/davidheineman/nlproc.tools/issues
Classifier: Programming Language :: Python :: 3
Classifier: License :: OSI Approved :: MIT License
Classifier: Operating System :: OS Independent
Requires-Python: >=3.6
License-File: LICENSE
Requires-Dist: pyyaml
Requires-Dist: deepdiff
